maxPooling.v
/*
	Author: Aniket Badhan
	Description: Max Pooling implementation (to find out the max of the 4 inputs of 2X2 sub matrix	)
*/

`timescale 1ns / 1ps

module maxPooling(
    input clk,
	input [21:0] input1,
	input [21:0] input2,
	input [21:0] input3,
	input [21:0] input4,
	input enable,
    output reg signed [21:0] output1,
	output reg maxPoolingDone
    );
	
	reg [21:0] initialMax = 22'b1000000000000000000000;
	reg [21:0] tempOutput;
	
	always @ (posedge clk) begin
		if(enable) begin
			if($signed(initialMax) < $signed(input1)) begin
				if($signed(input2) < $signed(input1)) begin
					if($signed(input3) < $signed(input1)) begin
						if($signed(input4) < $signed(input1)) begin
							output1 <= input1;
							maxPoolingDone <= 1;
						end
						else begin
							output1 <= input4;
							maxPoolingDone <= 1;
						end
					end
					else begin
						if($signed(input3) < $signed(input4)) begin
							output1 <= input4;
							maxPoolingDone <= 1;
						end
						else begin
							output1 <= input3;
							maxPoolingDone <= 1;
						end
					end
				end
				else begin
					if($signed(input3) < $signed(input2)) begin
						if($signed(input4) < $signed(input2)) begin
							output1 <= input2;
							maxPoolingDone <= 1;
						end
						else begin
							output1 <= input4;
							maxPoolingDone <= 1;
						end
					end
					else begin
						if($signed(input3) < $signed(input4)) begin
							output1 <= input4;
							maxPoolingDone <= 1;
						end
						else begin
							output1 <= input3;
							maxPoolingDone <= 1;
						end
					end
				end
			end
			else begin
				output1 <= initialMax;
				maxPoolingDone <= 1;
			end
		end
		else begin
			output1 <= 0;
			maxPoolingDone <= 0;
		end
	end


endmodule

maxPooling_tb.v
`timescale 1ns / 1ps

module maxPooling_tb;

	// Inputs
	reg [21:0] input1_layer1;
	reg [21:0] input2_layer1;
	reg [21:0] input3_layer1;
	reg [21:0] input4_layer1;

	reg [21:0] input1_layer2;
	reg [21:0] input2_layer2;
	reg [21:0] input3_layer2;
	reg [21:0] input4_layer2;
	reg [21:0] output_final;
	reg clk;
	reg layer1_en;
	reg layer2_en;
    reg layer1_done;
	reg layer2_done;
	// Outputs
	wire [21:0] output_layer1;
	wire [21:0] output_layer2;
	wire maxPoolingDone_layer1;
	wire maxPoolingDone_layer2;
	
	reg [21:0] array_image [0:63];
	reg [21:0] matrix_layer_2 [0:15] ;
	integer i = 0;
	integer j = 0;
	integer k = 0;
    integer l = 4;
	integer sum =0;

	// Instantiate the Unit Under Test (UUT)
	maxPooling uut1 (
		.input1(input1_layer1), 
		.input2(input2_layer1), 
		.input3(input3_layer1), 
		.input4(input4_layer1), 
		.clk(clk), 
		.enable(layer1_en), 
		.output1(output_layer1), 
		.maxPoolingDone(maxPoolingDone_layer1)
	);
	maxPooling uut2 (
		.input1(input1_layer2), 
		.input2(input2_layer2), 
		.input3(input3_layer2), 
		.input4(input4_layer2), 
		.clk(clk), 
		.enable(layer2_en), 
		.output1(output_layer2), 
		.maxPoolingDone(maxPoolingDone_layer2)
	);
	
	initial begin
		clk = 0;
		sum = 0;
		layer1_en = 0;
		layer2_en = 0;
		input1_layer1 = 0;
		input2_layer1 = 0;
		input3_layer1 = 0;
		input4_layer1 = 0;

		input1_layer2 = 0;
		input2_layer2 = 0;
		input3_layer2 = 0;
		input4_layer2 = 0;
		//set 1
		array_image[ 0 ] =  66 ;
        array_image[ 1 ] =  43 ;
        array_image[ 2 ] =  0 ;
        array_image[ 3 ] =  23 ;
		//set 2     
        array_image[ 4 ] =  112 ;
        array_image[ 5 ] =  43;
        array_image[ 6 ] =  45 ;
        array_image[ 7 ] =  23 ;
 		//set 3     
        array_image[ 8 ] =  44 ;
        array_image[ 9 ] =  55 ;
        array_image[ 10 ] =  51 ;
        array_image[ 11 ] =  22 ;
		//set 4
        array_image[ 12 ] =  32 ;
        array_image[ 13 ] =  44 ;
        array_image[ 14 ] =  112 ;
        array_image[ 15 ] =  56;
		//set 5
        array_image[ 16 ] =  87 ;
        array_image[ 17 ] =  11 ;
        array_image[ 18 ] =  56 ;
        array_image[ 19 ] =  32 ;
		//set 6
        array_image[ 20 ] =  29 ;
        array_image[ 21 ] =  11 ;
        array_image[ 22 ] =  0 ;
        array_image[ 23 ] =  32 ;
		//set 7      
        array_image[ 24 ] =  32 ;
        array_image[ 25 ] =  33 ;
        array_image[ 26 ] =  112 ;
        array_image[ 27 ] =  44;
		//set 8      
        array_image[ 28 ] =  43 ;
        array_image[ 29 ] =  66 ;
        array_image[ 30 ] =  21 ;
        array_image[ 31 ] =  88 ;
 		//set 9     
        array_image[ 32 ] =  123 ;
        array_image[ 33 ] =  45;
        array_image[ 34 ] =  11 ;
        array_image[ 35 ] =  67 ;
 		//set 10     
        array_image[ 36 ] =  54 ;
        array_image[ 37 ] =  332 ;
        array_image[ 38 ] =  32 ;
        array_image[ 39 ] =  112 ;
 		//set 11      
        array_image[ 40 ] =  43;
        array_image[ 41 ] =  11 ;
        array_image[ 42 ] =  214 ;
        array_image[ 43 ] =  31;
 		//set 12     
        array_image[ 44 ] =  80 ;
        array_image[ 45 ] =  97 ;
        array_image[ 46 ] =  98 ;
        array_image[ 47 ] =  112 ;
 		//set 13     
        array_image[ 48 ] =  55 ;
        array_image[ 49 ] =  32 ;
        array_image[ 50 ] =  11 ;
        array_image[ 51 ] =  11 ;
 		//set 14     
        array_image[ 52 ] =  56 ;
        array_image[ 53 ] =  99 ;
        array_image[ 54 ] =  77;
        array_image[ 55 ] =  88 ;
 		//set 15     
        array_image[ 56 ] =  0 ;
        array_image[ 57 ] =  55 ;
        array_image[ 58 ] =  112 ;
        array_image[ 59 ] =  44;
 		//set 16     
        array_image[ 60 ] =  39 ;
        array_image[ 61 ] =  11 ;
        array_image[ 62 ] =  0 ;
        array_image[ 63 ] =  88 ;

	end
	
	always #5 clk = ~clk;	
	
	always @ (posedge clk) begin
		if(i < 64) begin
			layer1_en = 1;
			input1_layer1 = array_image[i];
			input2_layer1 = array_image[i+1];
			input3_layer1 = array_image[i+2];
			input4_layer1 = array_image[i+3];
			i = i + 4;
			 #10;
			// sum = sum + output_layer1;
			// #2;
            matrix_layer_2[j]=output_layer1;
			// #10;
            j=j+1; 
	         #2;
		 end
		else 
		 begin
		  layer1_en = 0;
          layer1_done = 1;
		 end
	end

	always @(posedge clk) begin
		if(l <= 14 && k <= 10 && layer1_done==1 )
		 begin
			layer2_en=1;
			#10;
			input1_layer2 = matrix_layer_2[k];
			input2_layer2 = matrix_layer_2[k+1];
			input3_layer2 = matrix_layer_2[l];
			input4_layer2 = matrix_layer_2[l+1];
			#10;
			sum = sum + output_layer2;
			#10;
			if ( k ==2 )
			begin
			k = 8;
			l =12;
			end
			else 
			begin
			k= k+2;
			l = l+2;
			end	
		 end
		 else
		  begin
			#2;
			layer2_en=0;
			layer2_done=1;
		  end
	end

	always @(negedge layer2_en) begin
		$display("Final sum =%d",sum);
		#10;	
	end

	always @(posedge clk) begin
		// $display("Final sum =%d",sum);
		$dumpfile("maxpooler.vcd");
		$dumpvars;
		#1000
		$finish;		
	end     
endmodule

maxpooler.vcd
$date
	Thu Sep 21 12:03:18 2023
$end
$version
	Icarus Verilog
$end
$timescale
	1ps
$end
$scope module maxPooling_tb $end
$var wire 22 ! output_layer2 [21:0] $end
$var wire 22 " output_layer1 [21:0] $end
$var wire 1 # maxPoolingDone_layer2 $end
$var wire 1 $ maxPoolingDone_layer1 $end
$var reg 1 % clk $end
$var reg 22 & input1_layer1 [21:0] $end
$var reg 22 ' input1_layer2 [21:0] $end
$var reg 22 ( input2_layer1 [21:0] $end
$var reg 22 ) input2_layer2 [21:0] $end
$var reg 22 * input3_layer1 [21:0] $end
$var reg 22 + input3_layer2 [21:0] $end
$var reg 22 , input4_layer1 [21:0] $end
$var reg 22 - input4_layer2 [21:0] $end
$var reg 1 . layer1_done $end
$var reg 1 / layer1_en $end
$var reg 1 0 layer2_done $end
$var reg 1 1 layer2_en $end
$var integer 32 2 i [31:0] $end
$var integer 32 3 j [31:0] $end
$var integer 32 4 k [31:0] $end
$var integer 32 5 l [31:0] $end
$var integer 32 6 sum [31:0] $end
$scope module uut1 $end
$var wire 1 % clk $end
$var wire 1 / enable $end
$var wire 22 7 input1 [21:0] $end
$var wire 22 8 input2 [21:0] $end
$var wire 22 9 input3 [21:0] $end
$var wire 22 : input4 [21:0] $end
$var reg 22 ; initialMax [21:0] $end
$var reg 1 $ maxPoolingDone $end
$var reg 22 < output1 [21:0] $end
$upscope $end
$scope module uut2 $end
$var wire 1 % clk $end
$var wire 1 1 enable $end
$var wire 22 = input1 [21:0] $end
$var wire 22 > input2 [21:0] $end
$var wire 22 ? input3 [21:0] $end
$var wire 22 @ input4 [21:0] $end
$var reg 22 A initialMax [21:0] $end
$var reg 1 # maxPoolingDone $end
$var reg 22 B output1 [21:0] $end
$upscope $end
$upscope $end
$enddefinitions $end
$comment Show the parameter values. $end
$dumpall
$end
#5000
$dumpvars
b0 B
b1000000000000000000000 A
b0 @
b0 ?
b0 >
b0 =
b1000010 <
b1000000000000000000000 ;
b10111 :
b0 9
b101011 8
b1000010 7
b0 6
b100 5
b0 4
b0 3
b100 2
01
x0
1/
x.
b0 -
b10111 ,
b0 +
b0 *
b0 )
b101011 (
b0 '
b1000010 &
1%
1$
0#
b1000010 "
b0 !
$end
#7000
10
#10000
0%
#15000
1%
b1 3
#20000
0%
#25000
b1110000 "
b1110000 <
b1000 2
b101101 *
b101101 9
b1110000 &
b1110000 7
1%
#30000
0%
#35000
1%
b10 3
#40000
0%
#45000
b110111 "
b110111 <
b1100 2
b10110 ,
b10110 :
b110011 *
b110011 9
b110111 (
b110111 8
b101100 &
b101100 7
1%
#50000
0%
#55000
1%
b11 3
#60000
0%
#65000
b1110000 "
b1110000 <
b10000 2
b111000 ,
b111000 :
b1110000 *
b1110000 9
b101100 (
b101100 8
b100000 &
b100000 7
1%
#70000
0%
#75000
1%
b100 3
#80000
0%
#85000
b1010111 "
b1010111 <
b10100 2
b100000 ,
b100000 :
b111000 *
b111000 9
b1011 (
b1011 8
b1010111 &
b1010111 7
1%
#90000
0%
#95000
1%
b101 3
#100000
0%
#105000
b100000 "
b100000 <
b11000 2
b0 *
b0 9
b11101 &
b11101 7
1%
#110000
0%
#115000
1%
b110 3
#120000
0%
#125000
b1110000 "
b1110000 <
b11100 2
b101100 ,
b101100 :
b1110000 *
b1110000 9
b100001 (
b100001 8
b100000 &
b100000 7
1%
#130000
0%
#135000
1%
b111 3
#140000
0%
#145000
b1011000 "
b1011000 <
b100000 2
b1011000 ,
b1011000 :
b10101 *
b10101 9
b1000010 (
b1000010 8
b101011 &
b101011 7
1%
#150000
0%
#155000
1%
b1000 3
#160000
0%
#165000
b1111011 "
b1111011 <
b100100 2
b1000011 ,
b1000011 :
b1011 *
b1011 9
b101101 (
b101101 8
b1111011 &
b1111011 7
1%
#170000
0%
#175000
1%
b1001 3
#180000
0%
#185000
b101001100 "
b101001100 <
b101000 2
b1110000 ,
b1110000 :
b100000 *
b100000 9
b101001100 (
b101001100 8
b110110 &
b110110 7
1%
#190000
0%
#195000
1%
b1010 3
#200000
0%
#205000
b11010110 "
b11010110 <
b101100 2
b11111 ,
b11111 :
b11010110 *
b11010110 9
b1011 (
b1011 8
b101011 &
b101011 7
1%
#210000
0%
#215000
1%
b1011 3
#220000
0%
#225000
b1110000 "
b1110000 <
b110000 2
b1110000 ,
b1110000 :
b1100010 *
b1100010 9
b1100001 (
b1100001 8
b1010000 &
b1010000 7
1%
#230000
0%
#235000
1%
b1100 3
#240000
0%
#245000
b110111 "
b110111 <
b110100 2
b1011 ,
b1011 :
b1011 *
b1011 9
b100000 (
b100000 8
b110111 &
b110111 7
1%
#250000
0%
#255000
1%
b1101 3
#260000
0%
#265000
b1100011 "
b1100011 <
b111000 2
b1011000 ,
b1011000 :
b1001101 *
b1001101 9
b1100011 (
b1100011 8
b111000 &
b111000 7
1%
#270000
0%
#275000
1%
b1110 3
#280000
0%
#285000
b1110000 "
b1110000 <
b111100 2
b101100 ,
b101100 :
b1110000 *
b1110000 9
b110111 (
b110111 8
b0 &
b0 7
1%
#290000
0%
#295000
1%
b1111 3
#300000
0%
#305000
b1011000 "
b1011000 <
b1000000 2
b1011000 ,
b1011000 :
b0 *
b0 9
b1011 (
b1011 8
b100111 &
b100111 7
1%
#310000
0%
#315000
1%
b10000 3
#320000
0%
#325000
0$
b0 "
b0 <
1.
0/
1%
#330000
0%
#335000
1#
11
1%
#340000
0%
#345000
b1110000 !
b1110000 B
1%
b100000 -
b100000 @
b1010111 +
b1010111 ?
b1110000 )
b1110000 >
b1000010 '
b1000010 =
#350000
0%
#355000
1%
b1110000 6
#360000
0%
#365000
1%
b110 5
b10 4
#370000
0%
#375000
1%
b1011000 -
b1011000 @
b1110000 +
b1110000 ?
b110111 '
b110111 =
#380000
0%
#385000
1%
b11100000 6
#390000
0%
#395000
1%
b1100 5
b1000 4
#400000
0%
#405000
b101001100 !
b101001100 B
1%
b1100011 -
b1100011 @
b110111 +
b110111 ?
b101001100 )
b101001100 >
b1111011 '
b1111011 =
#410000
0%
#415000
1%
b1000101100 6
#420000
0%
#425000
1%
b1110 5
b1010 4
#430000
0%
#435000
b11010110 !
b11010110 B
1%
b1011000 -
b1011000 @
b1110000 +
b1110000 ?
b1110000 )
b1110000 >
b11010110 '
b11010110 =
#440000
0%
#445000
1%
b1100000010 6
#450000
0%
#455000
1%
b10000 5
b1100 4
#457000
01
#460000
0%
#465000
0#
b0 !
b0 B
1%
